pose_estimation_recognition_utils_rtmlib/Image2DResult.py
pose_estimation_recognition_utils_rtmlib/Image3DResult.py
pose_estimation_recognition_utils_rtmlib/RTMPoseEstimationFrom3DFrame.py
pose_estimation_recognition_utils_rtmlib/RTMPoseNames.py
pose_estimation_recognition_utils_rtmlib/Simple3DPoseLiftingModel.py
pose_estimation_recognition_utils_rtmlib/Video2DResult.py
pose_estimation_recognition_utils_rtmlib/Video3DResult.py
pose_estimation_recognition_utils_rtmlib/__init__.py
pose_estimation_recognition_utils_rtmlib/model_loader.py
pose_estimation_recognition_utils_rtmlib/rtm_lifting.py
pose_estimation_recognition_utils_rtmlib/rtm_pose_estimator_2d.py
pose_estimation_recognition_utils_rtmlib/rtm_pose_estimator_3d.py
pose_estimation_recognition_utils_rtmlib/utils.py
pose_estimation_recognition_utils_rtmlib-0.1.4.dist-info/METADATA
pose_estimation_recognition_utils_rtmlib-0.1.4.dist-info/WHEEL
pose_estimation_recognition_utils_rtmlib-0.1.4.dist-info/top_level.txt
pose_estimation_recognition_utils_rtmlib-0.1.4.dist-info/RECORD
