Metadata-Version: 2.4
Name: pose-estimation-recognition-utils-rtmlib
Version: 0.1.4
Summary: Classes for AI recognition on pose estimation data with rtmlib
Home-page: https://github.com/cobtras/pose-estimation-recognition-utils-rtmlib
Author: Jonas David Stephan, Sabine Dawletow, Nathalie Dollmann, Benjamin Otto Ernst Bruch
Author-email: j.stephan@system-systeme.de
License: Apache 2.0
Requires-Dist: setuptools>=70.0.0
Requires-Dist: pose-estimation-recognition-utils>=0.3.0
Requires-Dist: rtmlib>=0.0.14
Requires-Dist: tqdm>=1.0
Requires-Dist: huggingface-hub>=0.9.0
Requires-Dist: torch>=2.4.0
Dynamic: author
Dynamic: author-email
Dynamic: description
Dynamic: home-page
Dynamic: license
Dynamic: requires-dist
Dynamic: summary
